{
    "actions": [],
    "binder": {
        "className": "org.joget.plugin.enterprise.JdbcDataListBinder",
        "properties": {
            "jdbcDatasource": "default",
            "optimisePaging": "",
            "primaryKey": "id",
            "sql": "SELECT id, c_id_processo, c_nome_atividade, c_data_inicio, c_data_fim FROM app_fd_sla_atividade"
        }
    },
    "buttonPosition": "bottomLeft",
    "checkboxPosition": "left",
    "columns": [],
    "considerFilterWhenGetTotal": "",
    "description": "",
    "disableResponsive": "",
    "filters": [],
    "hidePageSize": "",
    "id": "erm_teste2",
    "name": "erm_teste2",
    "order": "1",
    "orderBy": "",
    "pageSize": "0",
    "pageSizeSelectorOptions": "10,20,30,40,50,100",
    "responsiveView": [
        {
            "breakpoint": "",
            "columns": "",
            "view": "Mobile"
        },
        {
            "breakpoint": "",
            "columns": "",
            "view": "Tablet"
        }
    ],
    "rowActions": [],
    "searchPopup": "",
    "showDataWhenFilterSet": "",
    "showPageSizeSelector": "true",
    "useSession": ""
}