{
    "actions": [],
    "binder": {
        "className": "org.joget.plugin.enterprise.AdvancedFormRowDataListBinder",
        "properties": {"formDefId": "informacaoColaboradores"}
    },
    "buttonPosition": "bottomLeft",
    "checkboxPosition": "left",
    "columns": [
        {
            "action": {
                "className": "",
                "properties": {}
            },
            "alignment": "",
            "datalist_type": "column",
            "exclude_export": "",
            "format": {
                "className": "",
                "properties": {}
            },
            "headerAlignment": "",
            "hidden": "false",
            "id": "column_0",
            "label": "Colaborador",
            "name": "user_colaborador",
            "sortable": "false",
            "style": "",
            "width": ""
        },
        {
            "id": "column_1",
            "label": "Data de Nascimento",
            "name": "data_nascimento"
        },
        {
            "id": "column_2",
            "label": "Departamento",
            "name": "departamento"
        },
        {
            "id": "column_3",
            "label": "ID",
            "name": "id"
        },
        {
            "id": "column_4",
            "label": "Nacionalidade",
            "name": "nacionalidade"
        }
    ],
    "considerFilterWhenGetTotal": "",
    "description": "",
    "disableResponsive": "",
    "filters": [],
    "hidePageSize": "",
    "id": "list_informacaoColaboradores",
    "name": "List - Colaboradores",
    "order": "",
    "orderBy": "",
    "pageSize": "0",
    "pageSizeSelectorOptions": "10,20,30,40,50,100",
    "responsiveView": [
        {
            "breakpoint": "",
            "columns": "",
            "view": "Mobile"
        },
        {
            "breakpoint": "",
            "columns": "",
            "view": "Tablet"
        }
    ],
    "rowActions": [],
    "searchPopup": "",
    "showDataWhenFilterSet": "",
    "showPageSizeSelector": "true",
    "useSession": ""
}